<?xml version="1.0"?>
<!--

    PHR_JavaWebService

    Copyright (C) 1999-2014 Photon Infotech Inc.

    Licensed under the Apache License, Version 2.0 (the "License");
    you may not use this file except in compliance with the License.
    You may obtain a copy of the License at

            http://www.apache.org/licenses/LICENSE-2.0

    Unless required by applicable law or agreed to in writing, software
    distributed under the License is distributed on an "AS IS" BASIS,
    WITHOUT WARRANTIES OR CONDITIONS OF ANY KIND, either express or implied.
    See the License for the specific language governing permissions and
    limitations under the License.

-->
<!DOCTYPE hibernate-mapping PUBLIC
	"-//Hibernate/Hibernate Mapping DTD 3.0//EN"
	"http://hibernate.sourceforge.net/hibernate-mapping-3.0.dtd">
<hibernate-mapping>
	<class name="com.photon.phresco.eshop.models.UserHBM"	table="eshop_users">
		<meta attribute="class-description">
			This class contains the Product details.
	    </meta>
		<id name="userId" type="integer" column="user_id">
			<generator class="increment" />
		</id>
		<property name="userName" type="string" column="user_name" />
		<property name="userPassword" type="string" column="user_password" />
		<property name="userRegDate" type="date" column="user_regdate" />
		<property name="userLastLogin" type="date" column="user_last_login" />
	</class>

</hibernate-mapping>